agentlab/__init__.py
agentlab/_version.py
agentlab/ui_assistant.py
agentlab/agents/README.md
agentlab/agents/__init__.py
agentlab/agents/agent_args.py
agentlab/agents/agent_utils.py
agentlab/agents/debug_agent.py
agentlab/agents/dynamic_prompting.py
agentlab/agents/generic_agent/__init__.py
agentlab/agents/generic_agent/agent_configs.py
agentlab/agents/generic_agent/generic_agent.py
agentlab/agents/generic_agent/generic_agent_prompt.py
agentlab/agents/generic_agent/reproducibility_agent.py
agentlab/agents/generic_agent/tmlr_config.py
agentlab/agents/generic_agent_hinter/__init__.py
agentlab/agents/hint_use_agent/__init__.py
agentlab/agents/hint_use_agent/agent_configs.py
agentlab/agents/hint_use_agent/generic_agent.py
agentlab/agents/hint_use_agent/generic_agent_prompt.py
agentlab/agents/hint_use_agent/tmlr_config.py
agentlab/agents/hitl_agent/base_multi_candidate_agent.py
agentlab/agents/hitl_agent/generic_human_guided_agent.py
agentlab/agents/hitl_agent/hint_labelling.py
agentlab/agents/hitl_agent/hitl_agent.py
agentlab/agents/hitl_agent/launch_hint_ui.py
agentlab/agents/hitl_agent/multi_candidate_generic_agent.py
agentlab/agents/hitl_agent/hint_labelling_ui_files/hint_labeling_ui.html
agentlab/agents/most_basic_agent/__init__.py
agentlab/agents/most_basic_agent/most_basic_agent.py
agentlab/agents/tapeagent/__init__.py
agentlab/agents/tapeagent/agent.py
agentlab/agents/tapeagent/conf/gaia_l1.yaml
agentlab/agents/tapeagent/conf/gaia_val.yaml
agentlab/agents/tapeagent/conf/agent/plan_act.yaml
agentlab/agents/tapeagent/conf/agent/plan_react.yaml
agentlab/agents/tapeagent/conf/environment/web_code.yaml
agentlab/agents/tapeagent/conf/llm/gpt4o.yaml
agentlab/agents/tapeagent/conf/llm/gpt4o_mini.yaml
agentlab/agents/tapeagent/conf/llm/o4mini.yaml
agentlab/agents/tapeagent/experiments/run_gaia.py
agentlab/agents/tapeagent/experiments/setup_gaia.sh
agentlab/agents/tool_use_agent/__init__.py
agentlab/agents/tool_use_agent/cua_like_agent.py
agentlab-0.4.2.dist-info/METADATA
agentlab-0.4.2.dist-info/WHEEL
agentlab-0.4.2.dist-info/entry_points.txt
agentlab-0.4.2.dist-info/licenses/LICENSE
agentlab-0.4.2.dist-info/RECORD
