Metadata-Version: 2.4
Name: agentlab
Version: 0.4.2
Summary: Main package for developing agents and experiments
Project-URL: Homepage, https://github.com/ServiceNow/AgentLab
Author-email: Rim Assouel <rim.assouel@gmail.com>, Alex Drouin <alex.drouin@servicenow.com>, Maxime Gasse <maxime.gasse@servicenow.com>, Alex Lacoste <alex.lacoste@servicenow.com>, Tom Marty <tom.marty@polymtl.ca>, Massimo Caccia <massimo.caccia1@servicenow.com>, Thibault Le Sellier de Chezelles <thibault.de.chezelles@gmail.com>, Aman Jaiswal <aman.jaiswal@servicenow.com>
License: Apache-2.0
License-File: LICENSE
Classifier: Development Status :: 2 - Pre-Alpha
Classifier: Intended Audience :: Science/Research
Classifier: License :: OSI Approved :: Apache Software License
Classifier: Operating System :: OS Independent
Classifier: Programming Language :: Python :: 3
Classifier: Topic :: Scientific/Engineering :: Artificial Intelligence
Requires-Python: <3.13,>=3.11
Requires-Dist: anthropic>=0.62.0
Requires-Dist: browsergym>=0.7.1
Requires-Dist: contexttimer
Requires-Dist: dask
Requires-Dist: distributed
Requires-Dist: gitpython
Requires-Dist: gradio>=5.5
Requires-Dist: gymnasium>=0.27
Requires-Dist: huggingface-hub
Requires-Dist: ipython
Requires-Dist: joblib>=1.2.0
Requires-Dist: litellm>=1.75.3
Requires-Dist: matplotlib
Requires-Dist: openai<2,>=1.7
Requires-Dist: pandas
Requires-Dist: pillow
Requires-Dist: pydantic~=2.9
Requires-Dist: python-dotenv>=1.1.1
Requires-Dist: python-slugify
Requires-Dist: pyyaml>=6
Requires-Dist: ray[default]
Requires-Dist: requests
Requires-Dist: tiktoken
Requires-Dist: torch>=2.2.2
Provides-Extra: hint
Requires-Dist: sentence-transformers>=5.0.0; extra == 'hint'
Provides-Extra: transformers
Requires-Dist: transformers>=4.38.2; extra == 'transformers'
